picture_evo/__init__.py
picture_evo/__main__.py
picture_evo/evolution.py
picture_evo/fitness.py
picture_evo/helpers.py
picture_evo/main.py
picture_evo/species.py
picture_evo-0.1.dist-info/METADATA
picture_evo-0.1.dist-info/WHEEL
picture_evo-0.1.dist-info/top_level.txt
picture_evo-0.1.dist-info/RECORD
