Metadata-Version: 2.1
Name: picture-evo
Version: 0.1
Summary: 진화 알고리즘으로 김준영의 얼굴을 그려보자!
Home-page: https://github.com/hjg0706/picture_evo
Author: Hong Jungi
License: UNKNOWN
Platform: UNKNOWN
Classifier: Intended Audience :: Developers
Classifier: Intended Audience :: Science/Research
Classifier: Programming Language :: Python
Classifier: Programming Language :: Python :: 3
Classifier: Programming Language :: Python :: 3.6
Classifier: Programming Language :: Python :: 3.7
Classifier: Programming Language :: Python :: 3.8
Classifier: Programming Language :: Python :: 3.9
Requires-Python: >=3.6
Requires-Dist: opencv-python
Requires-Dist: numpy
Requires-Dist: matplotlib
Requires-Dist: scikit-image
Provides-Extra: test
Requires-Dist: pytest (<5.4.0) ; extra == 'test'
Requires-Dist: pytest-cov (==2.8.1) ; extra == 'test'
Requires-Dist: pytest-sugar (==0.9.2) ; extra == 'test'
Requires-Dist: black ; extra == 'test'
Requires-Dist: pre-commit ; extra == 'test'
Requires-Dist: flake8 ; extra == 'test'
Requires-Dist: mypy ; extra == 'test'
Requires-Dist: bandit ; extra == 'test'
